quant/README.md
quant/__init__.py
quant/__main__.py
quant/core/__init__.py
quant/core/benchmark.py
quant/core/builders.py
quant/core/checkpoint.py
quant/core/config.py
quant/core/distributed.py
quant/core/io.py
quant/core/logging.py
quant/core/meters.py
quant/core/net.py
quant/core/optimizer.py
quant/core/timer.py
quant/core/trainer.py
quant/datasets/__init__.py
quant/datasets/loader.py
quant/datasets/npz_dataset.py
quant/datasets/utils.py
quant/evaluate/__init__.py
quant/evaluate/football_test.py
quant/evaluate/meters.py
quant/evaluate/table20240326.py
quant/evaluate/table20240420.py
quant/evaluate/utils.py
quant/football/__init__.py
quant/football/data/__init__.py
quant/football/data/functional.py
quant/football/data/preprocessing.py
quant/football/data/sampler.py
quant/football/data/selection.py
quant/football/data/stats.py
quant/football/data/utils.py
quant/football/data/datasets/__init__.py
quant/football/data/datasets/base.py
quant/football/infer/README.md
quant/football/infer/__init__.py
quant/football/infer/fastapi_app.py
quant/football/infer/football_overunder_v1.py
quant/football/infer/test_fastapi.py
quant/football/models/__init__.py
quant/football/models/mtnet.py
quant/football/models/stnet.py
quant/football/models/goal/__init__.py
quant/football/models/goal/odds.py
quant/football/models/goal/team_event.py
quant/football/models/losses/__init__.py
quant/football/transforms/__init__.py
quant/football/transforms/table20240326.py
quant/football/transforms/table20240414.py
quant/football/transforms/table20240419.py
quant/football/transforms/table20240420.py
quant/football/transforms/table20240424.py
quant/layers/__init__.py
quant/layers/layer_scale.py
quant/layers/mlp.py
quant/layers/normalization.py
quant/layers/swiglu_ffn.py
quant/models/__init__.py
quant/models/npz_net.py
quant/models/utils.py
quant/utils/__init__.py
quant/utils/archive.py
quant/utils/config.py
quant/utils/io.py
quant/utils/logging.py
quant2-0.1.27.dist-info/entry_points.txt
quant2-0.1.27.dist-info/LICENSE
quant2-0.1.27.dist-info/WHEEL
quant2-0.1.27.dist-info/METADATA
quant2-0.1.27.dist-info/RECORD
