Metadata-Version: 2.1
Name: quant2
Version: 0.1.27
Summary: A collection of useful tools!
Author-email: Hejian <flystarhe@qq.com>
Requires-Python: >=3.10
Requires-Dist: flake8
Requires-Dist: numpy
Requires-Dist: prettytable
Requires-Dist: pyyaml
Requires-Dist: scikit-learn
Requires-Dist: torch
Requires-Dist: yacs
Project-URL: Home, https://github.com/flystarhe/quant
